<ListN>
  <item>
    <title>Inception</title>
    <year>2010</year>
    <genres>
      <genre>Action</genre>
      <genre>Adventure</genre>
      <genre>Sci-Fi</genre>
    </genres>
    <director>
      <fullName>Christopher Nolan</fullName>
      <name>Christopher</name>
      <surname>Nolan</surname>
    </director>
  </item>
  <item>
    <title>The Dark Knight</title>
    <year>2008</year>
    <genres>
      <genre>Action</genre>
      <genre>Crime</genre>
      <genre>Drama</genre>
    </genres>
    <director>
      <fullName>Christopher Nolan</fullName>
      <name>Christopher</name>
      <surname>Nolan</surname>
    </director>
  </item>
  <item>
    <title>The Lord of the Rings: The Fellowship of the Ring</title>
    <year>2001</year>
    <genres>
      <genre>Action</genre>
      <genre>Adventure</genre>
      <genre>Drama</genre>
    </genres>
    <director>
      <fullName>Peter Jackson</fullName>
      <name>Peter</name>
      <surname>Jackson</surname>
    </director>
  </item>
  <item>
    <title>Inception</title>
    <year>2010</year>
    <genres>
      <genre>Action</genre>
      <genre>Adventure</genre>
      <genre>Sci-Fi</genre>
    </genres>
    <director>
      <fullName>Christopher Nolan</fullName>
      <name>Christopher</name>
      <surname>Nolan</surname>
    </director>
  </item>
  <item>
    <title>The Dark Knight</title>
    <year>2008</year>
    <genres>
      <genre>Action</genre>
      <genre>Crime</genre>
      <genre>Drama</genre>
    </genres>
    <director>
      <fullName>Christopher Nolan</fullName>
      <name>Christopher</name>
      <surname>Nolan</surname>
    </director>
  </item>
  <item>
    <title>The Lord of the Rings: The Fellowship of the Ring</title>
    <year>2001</year>
    <genres>
      <genre>Action</genre>
      <genre>Adventure</genre>
      <genre>Drama</genre>
    </genres>
    <director>
      <fullName>Peter Jackson</fullName>
      <name>Peter</name>
      <surname>Jackson</surname>
    </director>
  </item>
</ListN>
